{"errors":[],"warnings":[],"namedChunkGroups":{"app":{"chunks":[5,0,1],"assets":["webpack-runtime-02631d4736802ca7d9ff.js","webpack-runtime-02631d4736802ca7d9ff.js.map","commons.e582780fc7b36c511d2d.css","commons-f798d312a72d5cc25e6b.js","commons-f798d312a72d5cc25e6b.js.map","app-9cf317fc9912ea6f90b7.js","app-9cf317fc9912ea6f90b7.js.map"],"children":{},"childAssets":{}},"component---src-pages-404-js":{"chunks":[0,2],"assets":["commons.e582780fc7b36c511d2d.css","commons-f798d312a72d5cc25e6b.js","commons-f798d312a72d5cc25e6b.js.map","component---src-pages-404-js-903b5c09952ee3db0c23.js","component---src-pages-404-js-903b5c09952ee3db0c23.js.map"],"children":{},"childAssets":{}},"component---src-pages-index-js":{"chunks":[0,4,3],"assets":["commons.e582780fc7b36c511d2d.css","commons-f798d312a72d5cc25e6b.js","commons-f798d312a72d5cc25e6b.js.map","styles.545966e7c619f5763dc0.css","styles-9583ae787b78fe1af141.js","styles-9583ae787b78fe1af141.js.map","component---src-pages-index-js-c0897e521a7ebca9cac8.js","component---src-pages-index-js-c0897e521a7ebca9cac8.js.map"],"children":{},"childAssets":{}}},"assetsByChunkName":{"app":["webpack-runtime-02631d4736802ca7d9ff.js","commons.e582780fc7b36c511d2d.css","commons-f798d312a72d5cc25e6b.js","app-9cf317fc9912ea6f90b7.js"],"component---src-pages-404-js":["commons.e582780fc7b36c511d2d.css","commons-f798d312a72d5cc25e6b.js","component---src-pages-404-js-903b5c09952ee3db0c23.js"],"component---src-pages-index-js":["commons.e582780fc7b36c511d2d.css","commons-f798d312a72d5cc25e6b.js","styles.545966e7c619f5763dc0.css","styles-9583ae787b78fe1af141.js","component---src-pages-index-js-c0897e521a7ebca9cac8.js"]}}